raise_module_not_found_error.py
raise_module_not_found_error-1.0.1.dist-info/LICENSE.txt
raise_module_not_found_error-1.0.1.dist-info/METADATA
raise_module_not_found_error-1.0.1.dist-info/WHEEL
raise_module_not_found_error-1.0.1.dist-info/top_level.txt
raise_module_not_found_error-1.0.1.dist-info/RECORD
