Metadata-Version: 2.1
Name: raise-module-not-found-error
Version: 1.0.1
Summary: Raises ModuleNotFoundError on import
Home-page: https://github.com/ralokt/raise-module-not-found-error/
Author: Thomas Kolar
Author-email: thomaskolar90@gmail.com
License: WTFPL
Keywords: useless
Platform: all
Classifier: Development Status :: 5 - Production/Stable
Classifier: Intended Audience :: Developers
Classifier: Intended Audience :: Other Audience
Classifier: Programming Language :: Python :: 3
Classifier: Operating System :: OS Independent
License-File: LICENSE.txt
